server.py
tripo_mcp-0.1.2.dist-info/licenses/LICENSE
tripo_mcp-0.1.2.dist-info/METADATA
tripo_mcp-0.1.2.dist-info/WHEEL
tripo_mcp-0.1.2.dist-info/entry_points.txt
tripo_mcp-0.1.2.dist-info/top_level.txt
tripo_mcp-0.1.2.dist-info/RECORD
