Metadata-Version: 2.4
Name: tripo-mcp
Version: 0.1.2
Summary: MCP (Model Control Protocol) integration for Tripo
Author-email: Allen Dang <allen@vastai3d.com>, pookiefoof <caoyanpei@gmail.com>, Ding Liang <liangding@vastai3d.com>
License: MIT
Keywords: mcp,blender,3d,automation
Classifier: Development Status :: 3 - Alpha
Classifier: Intended Audience :: Developers
Classifier: License :: OSI Approved :: MIT License
Classifier: Programming Language :: Python :: 3
Classifier: Programming Language :: Python :: 3.10
Requires-Python: >=3.10
License-File: LICENSE
Requires-Dist: tripo3d>=0.2.0
Requires-Dist: mcp[cli]>=1.4.1
Provides-Extra: dev
Dynamic: license-file
